pytest_test_utils/__init__.py
pytest_test_utils/_approx.py
pytest_test_utils/matchers.py
pytest_test_utils/py.typed
pytest_test_utils/pytest_plugin.py
pytest_test_utils/tmp_dir.py
pytest_test_utils/tmp_dir.pyi
pytest_test_utils/tmp_dir_factory.py
pytest_test_utils/waiters.py
pytest_test_utils-0.1.0.dist-info/LICENSE
pytest_test_utils-0.1.0.dist-info/METADATA
pytest_test_utils-0.1.0.dist-info/WHEEL
pytest_test_utils-0.1.0.dist-info/entry_points.txt
pytest_test_utils-0.1.0.dist-info/top_level.txt
pytest_test_utils-0.1.0.dist-info/RECORD
